siloworker/__init__.py
siloworker/client.py
siloworker/exceptions.py
siloworker/http.py
siloworker/types.py
siloworker/webhooks.py
siloworker_sdk-1.0.0.dist-info/METADATA
siloworker_sdk-1.0.0.dist-info/WHEEL
siloworker_sdk-1.0.0.dist-info/top_level.txt
siloworker_sdk-1.0.0.dist-info/RECORD
