Metadata-Version: 2.4
Name: siloworker-sdk
Version: 1.0.0
Summary: Official Python SDK for SiloWorker workflow automation platform
Author-email: SiloWorker <support@siloworker.dev>
License: MIT
Project-URL: Homepage, https://siloworker.dev
Project-URL: Documentation, https://docs.siloworker.dev
Project-URL: Repository, https://github.com/siloworker/siloworker-python-sdk
Project-URL: Bug Tracker, https://github.com/siloworker/siloworker-python-sdk/issues
Keywords: workflow,automation,jobs,queue,background-jobs,siloworker,api,sdk
Classifier: Development Status :: 5 - Production/Stable
Classifier: Intended Audience :: Developers
Classifier: License :: OSI Approved :: MIT License
Classifier: Programming Language :: Python :: 3
Classifier: Programming Language :: Python :: 3.8
Classifier: Programming Language :: Python :: 3.9
Classifier: Programming Language :: Python :: 3.10
Classifier: Programming Language :: Python :: 3.11
Classifier: Programming Language :: Python :: 3.12
Classifier: Topic :: Software Development :: Libraries :: Python Modules
Classifier: Topic :: Internet :: WWW/HTTP
Classifier: Topic :: System :: Distributed Computing
Requires-Python: >=3.8
Requires-Dist: requests>=2.25.0
Requires-Dist: typing-extensions>=4.0.0; python_version < "3.10"
Provides-Extra: dev
Requires-Dist: pytest>=7.0.0; extra == "dev"
Requires-Dist: pytest-asyncio>=0.21.0; extra == "dev"
Requires-Dist: pytest-cov>=4.0.0; extra == "dev"
Requires-Dist: black>=22.0.0; extra == "dev"
Requires-Dist: isort>=5.10.0; extra == "dev"
Requires-Dist: mypy>=1.0.0; extra == "dev"
Requires-Dist: flake8>=5.0.0; extra == "dev"
